velocitycmdb/__init__.py
velocitycmdb/arp_cat_cli.py
velocitycmdb/arp_cat_init_schema.py
velocitycmdb/arp_cat_loader.py
velocitycmdb/arp_cat_reset_test.py
velocitycmdb/arp_cat_util.py
velocitycmdb/assets_db_recovery.py
velocitycmdb/assets_netbox_gap.py
velocitycmdb/assets_netbox_sync.py
velocitycmdb/backup.py
velocitycmdb/build_from_csv.py
velocitycmdb/cli.py
velocitycmdb/component_reclassifier_v2.py
velocitycmdb/component_type_fixup.py
velocitycmdb/create_admin.py
velocitycmdb/create_users_db.py
velocitycmdb/db_doc.py
velocitycmdb/db_index_rebuild.py
velocitycmdb/db_init.py
velocitycmdb/db_load_fingerprints.py
velocitycmdb/db_loader_inventory.py
velocitycmdb/db_loader_inventory_cleanup.py
velocitycmdb/db_rebaseline.py
velocitycmdb/db_recover.py
velocitycmdb/db_to_sessions.py
velocitycmdb/debug1.py
velocitycmdb/desktop.py
velocitycmdb/fix_fts.py
velocitycmdb/fix_normalize_names.py
velocitycmdb/hammer.py
velocitycmdb/juniper_migration_batch.py
velocitycmdb/juniper_peer_report.py
velocitycmdb/map_monitor.py
velocitycmdb/multi_map_monitor.py
velocitycmdb/ospf_report.py
velocitycmdb/purge_capture_type.py
velocitycmdb/reset.py
velocitycmdb/restore.py
velocitycmdb/svg_interactive.py
velocitycmdb/svg_monitor.py
velocitycmdb/svg_parser.py
velocitycmdb/tfsm_fire.py
velocitycmdb/tfsm_fire_tester.py
velocitycmdb/tfsm_templates.db
velocitycmdb/topology-merge.py
velocitycmdb/trace_file.py
velocitycmdb/ttpfire.py
velocitycmdb/unpack_collection.py
velocitycmdb/velocitycmdb_import.py
velocitycmdb/app/__init__.py
velocitycmdb/app/config_loader.py
velocitycmdb/app/run.py
velocitycmdb/app/blueprints/__init__.py
velocitycmdb/app/blueprints/admin/__init__.py
velocitycmdb/app/blueprints/admin/maintenance_routes.py
velocitycmdb/app/blueprints/admin/maintenance_socktio.py
velocitycmdb/app/blueprints/admin/routes.py
velocitycmdb/app/blueprints/arp/__init__.py
velocitycmdb/app/blueprints/arp/routes.py
velocitycmdb/app/blueprints/assets/__init__.py
velocitycmdb-0.11.6.dist-info/licenses/LICENSE
velocitycmdb-0.11.6.dist-info/METADATA
velocitycmdb-0.11.6.dist-info/WHEEL
velocitycmdb-0.11.6.dist-info/entry_points.txt
velocitycmdb-0.11.6.dist-info/top_level.txt
velocitycmdb-0.11.6.dist-info/RECORD
