Metadata-Version: 2.4
Name: velocitycmdb
Version: 0.11.6
Summary: Tactical network CMDB with automated discovery, change detection, and operational intelligence
Home-page: https://github.com/scottpeterman/velocitycmdb
Author: Scott Peterman
Author-email: scottpeterman@gmail.com
Project-URL: Documentation, https://github.com/scottpeterman/velocitycmdb/blob/main/README.md
Project-URL: Source, https://github.com/scottpeterman/velocitycmdb
Project-URL: Tracker, https://github.com/scottpeterman/velocitycmdb/issues
Keywords: network,cmdb,discovery,monitoring,cisco,arista,juniper,netbox,automation,network-management,configuration-management,network-discovery,lldp,cdp,textfsm
Classifier: Development Status :: 4 - Beta
Classifier: Intended Audience :: System Administrators
Classifier: Intended Audience :: Information Technology
Classifier: Topic :: System :: Networking
Classifier: Topic :: System :: Networking :: Monitoring
Classifier: Topic :: System :: Systems Administration
Classifier: License :: OSI Approved :: MIT License
Classifier: Programming Language :: Python :: 3
Classifier: Programming Language :: Python :: 3.10
Classifier: Programming Language :: Python :: 3.11
Classifier: Programming Language :: Python :: 3.12
Classifier: Operating System :: OS Independent
Classifier: Environment :: Web Environment
Classifier: Framework :: Flask
Requires-Python: >=3.10
License-File: LICENSE
Requires-Dist: pyopenssl>=25.0.0
Requires-Dist: Flask>=3.1.2
Requires-Dist: Flask-SocketIO>=5.5.1
Requires-Dist: Werkzeug>=3.1.3
Requires-Dist: Jinja2>=3.1.6
Requires-Dist: MarkupSafe>=3.0.3
Requires-Dist: itsdangerous>=2.2.0
Requires-Dist: blinker>=1.9.0
Requires-Dist: python-socketio>=5.14.3
Requires-Dist: python-engineio>=4.12.3
Requires-Dist: bidict>=0.23.1
Requires-Dist: simple-websocket>=1.1.0
Requires-Dist: click>=8.3.0
Requires-Dist: paramiko>=4.0.0
Requires-Dist: netmiko>=4.6.0
Requires-Dist: napalm>=5.1.0
Requires-Dist: napalm-procurve>=0.6.0
Requires-Dist: ncclient>=0.7.0
Requires-Dist: pyserial>=3.5
Requires-Dist: scp>=0.15.0
Requires-Dist: textfsm>=2.1.0
Requires-Dist: ntc_templates>=8.1.0
Requires-Dist: ttp>=0.10.0
Requires-Dist: ttp-templates>=0.3.7
Requires-Dist: netutils>=1.15.1
Requires-Dist: mac_vendor_lookup>=0.1.10
Requires-Dist: cryptography>=46.0.0
Requires-Dist: junos-eznc>=2.7.5
Requires-Dist: lxml>=6.0.2
Requires-Dist: pyeapi>=1.0.4
Requires-Dist: pynxos>=0.0.5
Requires-Dist: networkx>=3.4
Requires-Dist: n2g>=0.3.0
Requires-Dist: matplotlib>=3.10.7
Requires-Dist: secure-cartography==0.9.5
Requires-Dist: python-igraph>=1.0.0
Requires-Dist: igraph>=1.0.0
Requires-Dist: PyYAML>=6.0.3
Requires-Dist: ruamel.yaml>=0.18.16
Requires-Dist: ruamel.yaml.clib>=0.2.14
Requires-Dist: yamlordereddictloader>=0.4.2
Requires-Dist: python-dotenv>=1.2.1
Requires-Dist: openpyxl>=3.1.5
Requires-Dist: et_xmlfile>=2.0.0
Requires-Dist: bcrypt>=5.0.0
Requires-Dist: cryptography>=46.0.3
Requires-Dist: PyNaCl>=1.6.0
Requires-Dist: ldap3>=2.9.1
Requires-Dist: requests>=2.32.5
Requires-Dist: requests-toolbelt>=1.0.0
Requires-Dist: urllib3>=2.5.0
Requires-Dist: certifi>=2025.10.5
Requires-Dist: h11>=0.16.0
Requires-Dist: wsproto>=1.2.0
Requires-Dist: netaddr>=1.3.0
Requires-Dist: pillow>=12.0.0
Requires-Dist: cairocffi>=1.7.1
Requires-Dist: CairoSVG>=2.8.2
Requires-Dist: contourpy>=1.3.0
Requires-Dist: cycler>=0.12.1
Requires-Dist: fonttools>=4.60.1
Requires-Dist: kiwisolver>=1.4.9
Requires-Dist: pyparsing>=3.2.5
Requires-Dist: numpy>=2.2.6
Requires-Dist: python-dateutil>=2.9.0.post0
Requires-Dist: six>=1.17.0
Requires-Dist: future>=1.0.0
Requires-Dist: func_timeout>=4.3.5
Requires-Dist: transitions>=0.9.3
Requires-Dist: texttable>=1.7.0
Requires-Dist: docutils>=0.22.3
Requires-Dist: markdown-it-py>=4.0.0
Requires-Dist: mdurl>=0.1.2
Requires-Dist: Pygments>=2.19.2
Requires-Dist: rich>=14.2.0
Requires-Dist: bleach>=6.3.0
Requires-Dist: defusedxml>=0.7.1
Requires-Dist: nh3>=0.3.2
Requires-Dist: cssselect2>=0.8.0
Requires-Dist: tinycss2>=1.4.0
Requires-Dist: webencodings>=0.5.1
Requires-Dist: cffi>=2.0.0
Requires-Dist: pycparser>=2.23
Requires-Dist: pyasn1>=0.6.1
Requires-Dist: setuptools>=80.9.0
Requires-Dist: wheel>=0.45.1
Requires-Dist: packaging>=25.0
Requires-Dist: pkginfo>=1.12.1.2
Requires-Dist: readme_renderer>=44.0
Requires-Dist: rfc3986>=2.0.0
Requires-Dist: importlib_metadata>=8.7.0
Requires-Dist: importlib_resources>=6.5.2
Requires-Dist: zipp>=3.23.0
Requires-Dist: typing_extensions>=4.15.0
Requires-Dist: jaraco.classes>=3.4.0
Requires-Dist: jaraco.context>=6.0.1
Requires-Dist: jaraco.functools>=4.3.0
Requires-Dist: more-itertools>=10.8.0
Requires-Dist: invoke>=2.2.1
Requires-Dist: keyring>=25.6.0
Requires-Dist: pywin32>=311; sys_platform == "win32"
Requires-Dist: pywin32-ctypes>=0.2.3; sys_platform == "win32"
Requires-Dist: WMI>=1.5.1; sys_platform == "win32"
Requires-Dist: colorama>=0.4.6; sys_platform == "win32"
Requires-Dist: PyQt6>=6.10.0
Requires-Dist: PyQt6-Qt6>=6.10.0
Requires-Dist: PyQt6-WebEngine>=6.10.0
Requires-Dist: PyQt6-WebEngine-Qt6>=6.10.0
Requires-Dist: PyQt6_sip>=13.10.2
Provides-Extra: windows
Requires-Dist: pywin32>=311; extra == "windows"
Requires-Dist: WMI>=1.5.1; extra == "windows"
Provides-Extra: linux
Requires-Dist: python-pam>=2.0.2; extra == "linux"
Provides-Extra: all
Requires-Dist: pywin32>=311; sys_platform == "win32" and extra == "all"
Requires-Dist: WMI>=1.5.1; sys_platform == "win32" and extra == "all"
Requires-Dist: python-pam>=2.0.2; sys_platform == "linux" and extra == "all"
Provides-Extra: dev
Requires-Dist: pytest>=7.0.0; extra == "dev"
Requires-Dist: pytest-cov>=4.0.0; extra == "dev"
Requires-Dist: black>=23.0.0; extra == "dev"
Requires-Dist: flake8>=6.0.0; extra == "dev"
Requires-Dist: mypy>=1.0.0; extra == "dev"
Provides-Extra: docs
Requires-Dist: sphinx>=5.0.0; extra == "docs"
Requires-Dist: sphinx-rtd-theme>=1.2.0; extra == "docs"
Dynamic: author
Dynamic: author-email
Dynamic: classifier
Dynamic: description
Dynamic: description-content-type
Dynamic: home-page
Dynamic: keywords
Dynamic: license-file
Dynamic: project-url
Dynamic: provides-extra
Dynamic: requires-dist
Dynamic: requires-python
Dynamic: summary
